blenderer/__init__.py
blenderer-0.0.1.data/data/LICENSE
blenderer-0.0.1.dist-info/LICENSE
blenderer-0.0.1.dist-info/METADATA
blenderer-0.0.1.dist-info/WHEEL
blenderer-0.0.1.dist-info/top_level.txt
blenderer-0.0.1.dist-info/RECORD
